.gitignore
.gitmodules
.project
CHANGES.txt
README.txt
buildout.cfg
rtd.txt
setup.cfg
setup.py
.externalToolBuilders/nosetests-repozitory.launch
docs/Makefile
docs/_themes
docs/conf.py
docs/index.rst
repozitory/__init__.py
repozitory/archive.py
repozitory/interfaces.py
repozitory/jsontype.py
repozitory/schema.py
repozitory.egg-info/PKG-INFO
repozitory.egg-info/SOURCES.txt
repozitory.egg-info/dependency_links.txt
repozitory.egg-info/entry_points.txt
repozitory.egg-info/not-zip-safe
repozitory.egg-info/requires.txt
repozitory.egg-info/top_level.txt
repozitory/tests/__init__.py
repozitory/tests/test_archive.py