Metadata-Version: 1.0
Name: repozitory
Version: 1.3
Summary: Simple document versioning for web apps, especially Pyramid apps.
Home-page: https://github.com/Pylons/repozitory
Author: Shane Hathaway
Author-email: shane@hathawaymix.org
License: BSD-derived (http://www.repoze.org/LICENSE.txt)
Keywords: pyramid pylons document version versioning sql sqlalchemy
Platform: UNKNOWN
